zim_mcp_server/__init__.py
zim_mcp_server/server.py
zim_mcp_server-0.1.0.dist-info/METADATA
zim_mcp_server-0.1.0.dist-info/WHEEL
zim_mcp_server-0.1.0.dist-info/entry_points.txt
zim_mcp_server-0.1.0.dist-info/licenses/LICENSE
zim_mcp_server-0.1.0.dist-info/RECORD
