Metadata-Version: 2.4
Name: zim-mcp-server
Version: 0.1.0
Summary: MCP server that enables AI models to access and search ZIM format knowledge bases offline
License-File: LICENSE
Requires-Python: >=3.12
Requires-Dist: beautifulsoup4>=4.13.4
Requires-Dist: html2text>=2025.4.15
Requires-Dist: libzim>=3.7.0
Requires-Dist: mcp[cli]>=1.9.0
